{
  "last-release-sha": "94466438443c6b3ff9eda9772dbfe39060910101",
  "packages": {
    ".": {
      "release-type": "node",
      "changelog-sections": [
        {
          "type": "feat",
          "section": "Features",
          "hidden": false
        },
        {
          "type": "feature",
          "section": "Features",
          "hidden": false
        },
        {
          "type": "fix",
          "section": "Bug Fixes",
          "hidden": false
        },
        {
          "type": "chore",
          "section": "Miscellaneous Chores",
          "hidden": false
        },
        {
          "type": "ci",
          "section": "Continuous Integration chores",
          "hidden": false
        }
      ],
      "skip-github-release": false,
      "bump-minor-pre-major": true,
      "bump-patch-for-minor-pre-major": false
    }
  }
}
